mantra_mixer
