Metadata-Version: 2.1
Name: mantra-mixer
Version: 0.6
Summary: Audio mixing library simplified.
Home-page: https://github.com/bossauh/mantra-mixer
Author: Philippe Mathew
Author-email: philmattdev@gmail.com
License: MIT
Download-URL: https://github.com/bossauh/mantra-mixer/archive/refs/tags/v_06.tar.gz
Keywords: audio,mixing,mixer
Platform: UNKNOWN
Classifier: Development Status :: 4 - Beta
Classifier: Intended Audience :: Developers
Classifier: Topic :: Software Development :: Build Tools
Classifier: License :: OSI Approved :: MIT License
Classifier: Programming Language :: Python :: 3.6
Classifier: Programming Language :: Python :: 3.7
License-File: LICENSE
